MANIFEST.in
setup.py
bin/qonos-api
bin/qonos-manage
bin/qonos-scheduler
bin/qonos-worker
qonos/__init__.py
qonos/netconf.py
qonos/version.py
qonos.egg-info/PKG-INFO
qonos.egg-info/SOURCES.txt
qonos.egg-info/dependency_links.txt
qonos.egg-info/requires.txt
qonos.egg-info/top_level.txt
qonos/api/__init__.py
qonos/api/api.py
qonos/api/versions.py
qonos/api/middleware/__init__.py
qonos/api/middleware/version_negotiation.py
qonos/api/middleware/openstack/__init__.py
qonos/api/v1/__init__.py
qonos/api/v1/api_utils.py
qonos/api/v1/job_metadata.py
qonos/api/v1/jobs.py
qonos/api/v1/router.py
qonos/api/v1/schedule_metadata.py
qonos/api/v1/schedules.py
qonos/api/v1/workers.py
qonos/common/__init__.py
qonos/common/config.py
qonos/common/exception.py
qonos/common/timeutils.py
qonos/common/utils.py
qonos/db/__init__.py
qonos/db/db_utils.py
qonos/db/migration.py
qonos/db/simple/__init__.py
qonos/db/simple/api.py
qonos/db/sqlalchemy/__init__.py
qonos/db/sqlalchemy/api.py
qonos/db/sqlalchemy/migration.py
qonos/db/sqlalchemy/models.py
qonos/db/sqlalchemy/migrate_repo/README
qonos/db/sqlalchemy/migrate_repo/__init__.py
qonos/db/sqlalchemy/migrate_repo/manage.py
qonos/db/sqlalchemy/migrate_repo/migrate.cfg
qonos/db/sqlalchemy/migrate_repo/schema.py
qonos/db/sqlalchemy/migrate_repo/versions/001_add_schedules_table.py
qonos/db/sqlalchemy/migrate_repo/versions/002_add_schedule_metadata_table.py
qonos/db/sqlalchemy/migrate_repo/versions/003_add_workers_table.py
qonos/db/sqlalchemy/migrate_repo/versions/004_add_jobs_table.py
qonos/db/sqlalchemy/migrate_repo/versions/005_add_job_metadata_table.py
qonos/db/sqlalchemy/migrate_repo/versions/006_add_job_faults_table.py
qonos/db/sqlalchemy/migrate_repo/versions/007_add_version_id_jobs.py
qonos/db/sqlalchemy/migrate_repo/versions/008_add_index_to_schedules.py
qonos/db/sqlalchemy/migrate_repo/versions/009_add_index_to_jobs.py
qonos/db/sqlalchemy/migrate_repo/versions/010_default_jobs_version_id.py
qonos/db/sqlalchemy/migrate_repo/versions/011_add_missing_foreign_keys_to_job_metadata.py
qonos/db/sqlalchemy/migrate_repo/versions/012_add_missing_foreign_keys_to_schedule_metadata.py
