Metadata-Version: 1.1
Name: qonos
Version: 1.1.5
Summary: The QonoS project provides services for scheduling regularly occuring tasks.
Home-page: UNKNOWN
Author: UNKNOWN
Author-email: UNKNOWN
License: Apache License (2.0)
Platform: UNKNOWN
Classifier: Development Status :: 2 - Pre-Alpha
Classifier: License :: OSI Approved :: Apache Software License
Classifier: Operating System :: POSIX :: Linux
Classifier: Programming Language :: Python :: 2.6
Classifier: Environment :: No Input/Output (Daemon)
Classifier: Environment :: OpenStack
